musicae/__init__.py
musicae/autosimilarity_segmentation.py
musicae/convolutional.py
musicae/data_manipulation.py
musicae/neural_nets_utils.py
musicae/model/__init__.py
musicae/model/current_plot.py
musicae/model/early_stopping.py
musicae/model/errors.py
musicae/model/features.py
musicae/scripts/__init__.py
musicae/scripts/default_path.py
musicae/scripts/overall_scripts.py
musicae/scripts/tests_article.py
musicae-0.1.2.dist-info/LICENSE.md
musicae-0.1.2.dist-info/METADATA
musicae-0.1.2.dist-info/WHEEL
musicae-0.1.2.dist-info/top_level.txt
musicae-0.1.2.dist-info/RECORD
