Metadata-Version: 2.1
Name: musicae
Version: 0.1.2
Summary: Package for single-song autoencoders applied on musical segmentation.
Home-page: https://gitlab.inria.fr/amarmore/musicae
Author: Marmoret Axel
Author-email: axel.marmoret@irisa.fr
License: BSD
Platform: UNKNOWN
Classifier: License :: OSI Approved :: BSD License
Classifier: Programming Language :: Python
Classifier: Development Status :: 3 - Alpha
Classifier: Intended Audience :: Developers
Classifier: Intended Audience :: Science/Research
Classifier: Topic :: Multimedia :: Sound/Audio :: Analysis
Classifier: Programming Language :: Python :: 3.8
Requires-Python: >=3.8.*
License-File: LICENSE.md
Requires-Dist: librosa (==0.8.0)
Requires-Dist: madmom (==0.16.1)
Requires-Dist: matplotlib
Requires-Dist: mir-eval (==0.6)
Requires-Dist: mirdata (==0.3.3)
Requires-Dist: numpy (==1.18.2)
Requires-Dist: pandas
Requires-Dist: scipy (>=1.4.1)
Requires-Dist: soundfile
Requires-Dist: tensorly (==0.5.1)
Requires-Dist: torch (==1.8.0)
